mmpxrt/__init__.py
mmpxrt/mmpxrt.py
mmpxrt-1.13.dist-info/LICENSE
mmpxrt-1.13.dist-info/METADATA
mmpxrt-1.13.dist-info/WHEEL
mmpxrt-1.13.dist-info/top_level.txt
mmpxrt-1.13.dist-info/RECORD
