Metadata-Version: 2.1
Name: mmpxrt
Version: 1.13
Summary: Raytracing code for x-ray (mosaic) spectrometers
Home-page: https://gitlab.hzdr.de/smid55/mmpxrt
Author: Michal Smid
Author-email: m.smid@hzdr.de
Classifier: Programming Language :: Python :: 3
Classifier: License :: OSI Approved :: MIT License
Classifier: Operating System :: OS Independent
Requires-Python: >=3.6
License-File: LICENSE
